[
	{
		"anonymous": false,
		"inputs": [
			{
				"indexed": true,
				"internalType": "address",
				"name": "fromToken",
				"type": "address"
			},
			{
				"indexed": true,
				"internalType": "address",
				"name": "toToken",
				"type": "address"
			},
			{
				"indexed": false,
				"internalType": "uint256",
				"name": "amount",
				"type": "uint256"
			},
			{
				"indexed": false,
				"internalType": "uint256",
				"name": "returnAmount",
				"type": "uint256"
			}
		],
		"name": "Swap",
		"type": "event"
	},
	{
		"inputs": [
			{
				"internalType": "address",
				"name": "fromToken",
				"type": "address"
			},
			{
				"internalType": "address",
				"name": "toToken",
				"type": "address"
			},
			{
				"internalType": "uint256",
				"name": "amount",
				"type": "uint256"
			}
		],
		"name": "getExpectedReturn",
		"outputs": [
			{
				"internalType": "uint256",
				"name": "",
				"type": "uint256"
			}
		],
		"stateMutability": "view",
		"type": "function"
	},
	{
		"inputs": [
			{
				"internalType": "address",
				"name": "token",
				"type": "address"
			}
		],
		"name": "getSwapRatio",
		"outputs": [
			{
				"internalType": "uint256",
				"name": "from",
				"type": "uint256"
			},
			{
				"internalType": "uint256",
				"name": "to",
				"type": "uint256"
			}
		],
		"stateMutability": "view",
		"type": "function"
	},
	{
		"inputs": [
			{
				"internalType": "address",
				"name": "token",
				"type": "address"
			},
			{
				"internalType": "uint256",
				"name": "fromAmount",
				"type": "uint256"
			},
			{
				"internalType": "uint256",
				"name": "toAmount",
				"type": "uint256"
			}
		],
		"name": "setSwapRatio",
		"outputs": [],
		"stateMutability": "nonpayable",
		"type": "function"
	},
	{
		"inputs": [
			{
				"internalType": "address[]",
				"name": "token",
				"type": "address[]"
			},
			{
				"internalType": "uint256[]",
				"name": "fromAmount",
				"type": "uint256[]"
			},
			{
				"internalType": "uint256[]",
				"name": "toAmount",
				"type": "uint256[]"
			}
		],
		"name": "setSwapRatioMulti",
		"outputs": [],
		"stateMutability": "nonpayable",
		"type": "function"
	},
	{
		"inputs": [
			{
				"internalType": "address",
				"name": "fromToken",
				"type": "address"
			},
			{
				"internalType": "address",
				"name": "toToken",
				"type": "address"
			},
			{
				"internalType": "uint256",
				"name": "amount",
				"type": "uint256"
			}
		],
		"name": "swap",
		"outputs": [
			{
				"internalType": "bool",
				"name": "",
				"type": "bool"
			}
		],
		"stateMutability": "payable",
		"type": "function"
	}
]
